poiidx/__about__.py
poiidx/__init__.py
poiidx/__main__.py
poiidx/administrativeBoundary.py
poiidx/baseModel.py
poiidx/country.py
poiidx/countryQuery.py
poiidx/example.py
poiidx/ext.py
poiidx/geofabrik.py
poiidx/osm.py
poiidx/pbf.py
poiidx/poi.py
poiidx/poiIdx.py
poiidx/poi_filter_config.yaml
poiidx/projection.py
poiidx/py.typed
poiidx/regionFinder.py
poiidx/scanner.py
poiidx/schemaHash.py
poiidx/system.py
poiidx-0.0.8.dist-info/METADATA
poiidx-0.0.8.dist-info/WHEEL
poiidx-0.0.8.dist-info/entry_points.txt
poiidx-0.0.8.dist-info/licenses/LICENSE.txt
poiidx-0.0.8.dist-info/RECORD
