Metadata-Version: 2.4
Name: poiidx
Version: 0.0.8
Summary: Efficient spatial indexing and querying of Points of Interest using PostgreSQL and PostGIS
Project-URL: Documentation, https://bytehexe.github.io/poiidx/
Project-URL: Issues, https://github.com/bytehexe/poiidx/issues
Project-URL: Source, https://github.com/bytehexe/poiidx
Author: Janna Hopp
License-Expression: MIT
License-File: LICENSE.txt
Classifier: Development Status :: 4 - Beta
Classifier: Programming Language :: Python
Classifier: Programming Language :: Python :: 3.8
Classifier: Programming Language :: Python :: 3.9
Classifier: Programming Language :: Python :: 3.10
Classifier: Programming Language :: Python :: 3.11
Classifier: Programming Language :: Python :: 3.12
Classifier: Programming Language :: Python :: Implementation :: CPython
Classifier: Programming Language :: Python :: Implementation :: PyPy
Requires-Python: >=3.8
Requires-Dist: coordinate-parser
Requires-Dist: osmium
Requires-Dist: peewee
Requires-Dist: platformdirs
Requires-Dist: psycopg2-binary
Requires-Dist: pyproj
Requires-Dist: pyyaml
Requires-Dist: requests
Requires-Dist: shapely
